[
  {
    "id": "bitcoin",
    "symbol": "btc",
    "name": "Bitcoin",
    "image": "https://coin-images.coingecko.com/coins/images/1/large/bitcoin.png?1696501400",
    "current_price": 93301,
    "market_cap": 1861069292982,
    "market_cap_rank": 1,
    "fully_diluted_valuation": 1861070224542,
    "total_volume": 42443170996,
    "high_24h": 95468,
    "low_24h": 92263,
    "price_change_24h": -1860.6842974773,
    "price_change_percentage_24h": -1.95529,
    "market_cap_change_24h": -40044372044.8997,
    "market_cap_change_percentage_24h": -2.10636,
    "circulating_supply": 19977993,
    "total_supply": 19978003,
    "max_supply": 21000000,
    "ath": 126080,
    "ath_change_percentage": -25.99875,
    "ath_date": "2025-10-06T18:57:42.558Z",
    "atl": 67.81,
    "atl_change_percentage": 137493.3671,
    "atl_date": "2013-07-06T00:00:00.000Z",
    "roi": null,
    "last_updated": "2026-01-19T17:15:01.775Z"
  },
  {
    "id": "ethereum",
    "symbol": "eth",
    "name": "Ethereum",
    "image": "https://coin-images.coingecko.com/coins/images/279/large/ethereum.png?1696501628",
    "current_price": 3221.45,
    "market_cap": 388469547716,
    "market_cap_rank": 2,
    "fully_diluted_valuation": 388469547716,
    "total_volume": 30991938764,
    "high_24h": 3364.25,
    "low_24h": 3190.76,
    "price_change_24h": -111.246219250291,
    "price_change_percentage_24h": -3.33802,
    "market_cap_change_24h": -14016224302.812,
    "market_cap_change_percentage_24h": -3.48241,
    "circulating_supply": 120694585.061123,
    "total_supply": 120694585.061123,
    "max_supply": null,
    "ath": 4946.05,
    "ath_change_percentage": -34.86812,
    "ath_date": "2025-08-24T19:21:03.333Z",
    "atl": 0.432979,
    "atl_change_percentage": 743921.18212,
    "atl_date": "2015-10-20T00:00:00.000Z",
    "roi": {
      "times": 45.1584817019564,
      "currency": "btc",
      "percentage": 4515.84817019564
    },
    "last_updated": "2026-01-19T17:15:02.755Z"
  },
  {
    "id": "tether",
    "symbol": "usdt",
    "name": "Tether",
    "image": "https://coin-images.coingecko.com/coins/images/325/large/Tether.png?1696501661",
    "current_price": 0.999492,
    "market_cap": 186902009280,
    "market_cap_rank": 3,
    "fully_diluted_valuation": 192366229839,
    "total_volume": 86359890215,
    "high_24h": 0.999695,
    "low_24h": 0.999316,
    "price_change_24h": -0.000182054696375333,
    "price_change_percentage_24h": -0.01821,
    "market_cap_change_24h": -27024288.3910522,
    "market_cap_change_percentage_24h": -0.01446,
    "circulating_supply": 186994926138.212,
    "total_supply": 192461863191.086,
    "max_supply": null,
    "ath": 1.32,
    "ath_change_percentage": -24.45858,
    "ath_date": "2018-07-24T00:00:00.000Z",
    "atl": 0.572521,
    "atl_change_percentage": 74.57613,
    "atl_date": "2015-03-02T00:00:00.000Z",
    "roi": null,
    "last_updated": "2026-01-19T17:15:10.780Z"
  },
  {
    "id": "binancecoin",
    "symbol": "bnb",
    "name": "BNB",
    "image": "https://coin-images.coingecko.com/coins/images/825/large/bnb-icon2_2x.png?1696501970",
    "current_price": 927.2,
    "market_cap": 126442079117,
    "market_cap_rank": 4,
    "fully_diluted_valuation": 126442079117,
    "total_volume": 2522569335,
    "high_24h": 952.61,
    "low_24h": 911.56,
    "price_change_24h": -21.8535883425221,
    "price_change_percentage_24h": -2.30267,
    "market_cap_change_24h": -3023962152.61107,
    "market_cap_change_percentage_24h": -2.33572,
    "circulating_supply": 136361043.33,
    "total_supply": 136361043.33,
    "max_supply": 200000000,
    "ath": 1369.99,
    "ath_change_percentage": -32.32061,
    "ath_date": "2025-10-13T08:41:24.131Z",
    "atl": 0.0398177,
    "atl_change_percentage": 2328517.87308,
    "atl_date": "2017-10-19T00:00:00.000Z",
    "roi": null,
    "last_updated": "2026-01-19T17:15:01.310Z"
  },
  {
    "id": "ripple",
    "symbol": "xrp",
    "name": "XRP",
    "image": "https://coin-images.coingecko.com/coins/images/44/large/xrp-symbol-white-128.png?1696501442",
    "current_price": 2.01,
    "market_cap": 122673422893,
    "market_cap_rank": 5,
    "fully_diluted_valuation": 201771551067,
    "total_volume": 4377270796,
    "high_24h": 2.06,
    "low_24h": 1.93,
    "price_change_24h": -0.0382804497080493,
    "price_change_percentage_24h": -1.86501,
    "market_cap_change_24h": -2227963237.56877,
    "market_cap_change_percentage_24h": -1.78378,
    "circulating_supply": 60789498738,
    "total_supply": 99985727631,
    "max_supply": 100000000000,
    "ath": 3.65,
    "ath_change_percentage": -44.75948,
    "ath_date": "2025-07-18T03:40:53.808Z",
    "atl": 0.00268621,
    "atl_change_percentage": 74885.97203,
    "atl_date": "2014-05-22T00:00:00.000Z",
    "roi": null,
    "last_updated": "2026-01-19T17:15:09.241Z"
  },
  {
    "id": "solana",
    "symbol": "sol",
    "name": "Solana",
    "image": "https://coin-images.coingecko.com/coins/images/4128/large/solana.png?1718769756",
    "current_price": 134.17,
    "market_cap": 75900407811,
    "market_cap_rank": 6,
    "fully_diluted_valuation": 83019827677,
    "total_volume": 5819214335,
    "high_24h": 142.92,
    "low_24h": 132.89,
    "price_change_24h": -7.76980152374907,
    "price_change_percentage_24h": -5.47408,
    "market_cap_change_24h": -4397926218.3988,
    "market_cap_change_percentage_24h": -5.47698,
    "circulating_supply": 565584583.558605,
    "total_supply": 618636131.451888,
    "max_supply": null,
    "ath": 293.31,
    "ath_change_percentage": -54.25749,
    "ath_date": "2025-01-19T11:15:27.957Z",
    "atl": 0.500801,
    "atl_change_percentage": 26690.72103,
    "atl_date": "2020-05-11T19:35:23.449Z",
    "roi": null,
    "last_updated": "2026-01-19T17:15:09.846Z"
  },
  {
    "id": "usd-coin",
    "symbol": "usdc",
    "name": "USDC",
    "image": "https://coin-images.coingecko.com/coins/images/6319/large/usdc.png?1696506694",
    "current_price": 0.999704,
    "market_cap": 75773705309,
    "market_cap_rank": 7,
    "fully_diluted_valuation": 75794659182,
    "total_volume": 6381964171,
    "high_24h": 0.999837,
    "low_24h": 0.999481,
    "price_change_24h": 0.00002763,
    "price_change_percentage_24h": 0.00276,
    "market_cap_change_24h": -183328015.810547,
    "market_cap_change_percentage_24h": -0.24136,
    "circulating_supply": 75793255877.0471,
    "total_supply": 75814215156.0623,
    "max_supply": null,
    "ath": 1.17,
    "ath_change_percentage": -14.74426,
    "ath_date": "2019-05-08T00:40:28.300Z",
    "atl": 0.877647,
    "atl_change_percentage": 13.9182,
    "atl_date": "2023-03-11T08:02:13.981Z",
    "roi": null,
    "last_updated": "2026-01-19T17:15:11.563Z"
  },
  {
    "id": "tron",
    "symbol": "trx",
    "name": "TRON",
    "image": "https://coin-images.coingecko.com/coins/images/1094/large/tron-logo.png?1696502193",
    "current_price": 0.309501,
    "market_cap": 29330287045,
    "market_cap_rank": 8,
    "fully_diluted_valuation": 29330286526,
    "total_volume": 852704531,
    "high_24h": 0.320419,
    "low_24h": 0.309249,
    "price_change_24h": -0.0091878323206992,
    "price_change_percentage_24h": -2.88301,
    "market_cap_change_24h": -859915872.821163,
    "market_cap_change_percentage_24h": -2.84833,
    "circulating_supply": 94709033745.3245,
    "total_supply": 94709032068.9674,
    "max_supply": null,
    "ath": 0.431288,
    "ath_change_percentage": -28.23802,
    "ath_date": "2024-12-04T00:10:40.323Z",
    "atl": 0.00180434,
    "atl_change_percentage": 17053.12866,
    "atl_date": "2017-11-12T00:00:00.000Z",
    "roi": {
      "times": 161.895285268345,
      "currency": "usd",
      "percentage": 16189.5285268345
    },
    "last_updated": "2026-01-19T17:15:10.712Z"
  },
  {
    "id": "staked-ether",
    "symbol": "steth",
    "name": "Lido Staked Ether",
    "image": "https://coin-images.coingecko.com/coins/images/13442/large/steth_logo.png?1696513206",
    "current_price": 3223.28,
    "market_cap": 29311400598,
    "market_cap_rank": 9,
    "fully_diluted_valuation": 29311400598,
    "total_volume": 49675826,
    "high_24h": 3363.8,
    "low_24h": 3190.75,
    "price_change_24h": -109.612548505281,
    "price_change_percentage_24h": -3.28882,
    "market_cap_change_24h": -674358390.293247,
    "market_cap_change_percentage_24h": -2.24893,
    "circulating_supply": 9104774.74121062,
    "total_supply": 9104774.74121062,
    "max_supply": null,
    "ath": 4932.89,
    "ath_change_percentage": -34.68254,
    "ath_date": "2025-08-24T19:21:31.902Z",
    "atl": 482.9,
    "atl_change_percentage": 567.23259,
    "atl_date": "2020-12-22T04:08:21.854Z",
    "roi": null,
    "last_updated": "2026-01-19T17:15:09.537Z"
  },
  {
    "id": "dogecoin",
    "symbol": "doge",
    "name": "Dogecoin",
    "image": "https://coin-images.coingecko.com/coins/images/5/large/dogecoin.png?1696501409",
    "current_price": 0.129062,
    "market_cap": 21724476739,
    "market_cap_rank": 10,
    "fully_diluted_valuation": 21725493443,
    "total_volume": 1964130443,
    "high_24h": 0.137749,
    "low_24h": 0.125946,
    "price_change_24h": -0.00756303349000956,
    "price_change_percentage_24h": -5.53561,
    "market_cap_change_24h": -1286464045.91682,
    "market_cap_change_percentage_24h": -5.59066,
    "circulating_supply": 168376333126.579,
    "total_supply": 168384213126.579,
    "max_supply": null,
    "ath": 0.731578,
    "ath_change_percentage": -82.3584,
    "ath_date": "2021-05-08T05:08:23.458Z",
    "atl": 0.0000869,
    "atl_change_percentage": 148411.48623,
    "atl_date": "2015-05-06T00:00:00.000Z",
    "roi": null,
    "last_updated": "2026-01-19T17:15:15.016Z"
  }
]